musicgen/__init__.py
musicgen/musicgen.py
musicgen-0.0.1.dist-info/LICENSE.txt
musicgen-0.0.1.dist-info/METADATA
musicgen-0.0.1.dist-info/WHEEL
musicgen-0.0.1.dist-info/top_level.txt
musicgen-0.0.1.dist-info/RECORD
