Metadata-Version: 2.1
Name: musicgen
Version: 0.0.1
Summary: A module for pre-processing steps in music generation
Home-page: https://github.com/ranjith-ms
Author: Ranjith M S
Author-email: ranjithms523@gmail.com
License: MIT
Download-URL: https://github.com/ranjith-ms/musicgen/archive/v0.1.tar.gz
Keywords: LSTM,Sequence models,RNN,Neural network,Music generation
Platform: UNKNOWN
Classifier: Programming Language :: Python :: 3
Classifier: Programming Language :: Python :: 3.4
Classifier: Programming Language :: Python :: 3.5
Classifier: Programming Language :: Python :: 3.6
Classifier: License :: OSI Approved :: MIT License
Classifier: Operating System :: OS Independent
Requires-Dist: youtube-dl
Requires-Dist: music21
Requires-Dist: numpy
